examples/demo.ipynb
examples/licensing.py
examples/link_conditioning.py
examples/sample.py
virl2_client/__init__.py
virl2_client/event_handling.py
virl2_client/event_listening.py
virl2_client/exceptions.py
virl2_client/models/__init__.py
virl2_client/models/annotation.py
virl2_client/models/auth_management.py
virl2_client/models/authentication.py
virl2_client/models/cl_pyats.py
virl2_client/models/configuration.py
virl2_client/models/group.py
virl2_client/models/groups.py
virl2_client/models/interface.py
virl2_client/models/lab.py
virl2_client/models/licensing.py
virl2_client/models/link.py
virl2_client/models/node.py
virl2_client/models/node_image_definition.py
virl2_client/models/node_image_definitions.py
virl2_client/models/resource_pool.py
virl2_client/models/resource_pools.py
virl2_client/models/smart_annotation.py
virl2_client/models/system.py
virl2_client/models/user.py
virl2_client/models/users.py
virl2_client/utils.py
virl2_client/virl2_client.py
virl2_client-2.9.0.dist-info/LICENSE
virl2_client-2.9.0.dist-info/METADATA
virl2_client-2.9.0.dist-info/NOTICE
virl2_client-2.9.0.dist-info/WHEEL
virl2_client-2.9.0.dist-info/RECORD
