Metadata-Version: 2.1
Name: virl2_client
Version: 2.9.0
Summary: VIRL2 Client Library
Home-page: https://github.com/ciscodevnet/virl2-client
License: Apache-2.0
Author: Simon Knight
Author-email: simknigh@cisco.com
Requires-Python: >=3.9.2,<4.0.0
Classifier: Development Status :: 4 - Beta
Classifier: Environment :: Console
Classifier: License :: OSI Approved :: Apache Software License
Classifier: Operating System :: OS Independent
Classifier: Programming Language :: Python :: 3
Classifier: Programming Language :: Python :: 3.10
Classifier: Programming Language :: Python :: 3.11
Classifier: Programming Language :: Python :: 3.12
Classifier: Programming Language :: Python :: 3.13
Classifier: Topic :: System :: Networking
Provides-Extra: docs
Provides-Extra: events
Provides-Extra: pyats
Requires-Dist: aiohttp (>=3.11.18,<3.12.0) ; extra == "events"
Requires-Dist: httpx (>=0.28.1,<0.29.0)
Requires-Dist: pyats (>=25,<26) ; extra == "pyats"
Requires-Dist: sphinx (>=7,<8) ; extra == "docs"
Requires-Dist: sphinx_rtd_theme (>=3,<4) ; extra == "docs"
Project-URL: Repository, https://github.com/ciscodevnet/virl2-client
